{"Soups": ["Housemade Chicken Noodle Soup", "Sweet Potato Curry Soup (V)"], "Plat Du Jour": ["Steamed White Rice (V)"], "Honor G Grill": ["Garlic Herb Cod", "Tartar Sauce", "Hamburger Char Grilled", "Char Grilled Cheeseburger", "Grilled Chicken Breast", "Beyond Burger (V)", "Mojo Fries"], "Roller Grill": ["Beef Hot Dog", "Coney Bun (V)", "Vegetarian Sweet Italian Sausage (V)", "Brats Bun (V)", "Chopped Yellow Onions (V)", "Sauerkraut (V)", "Sweet Green Pickle Relish (V)"], "Desserts": ["Ranger Cookies w-Coconut (OL)", "Granny's Spice Bars (V)"]}